{
    "intExample": 5,
    "strExample": "Hello!",
    "boolExample": [
        false,
        false,
        false,
        false
    ],
    "idSave": 16,
    "Coins": 2175,
    "Unlockers": 15,
    "Fillers": 15,
    "Removers": 16,
    "Breakers": 15,
    "BlocksColorized": 0,
    "LastLevelIndex": 6,
    "PassedLevelIndexes": [
        1,
        2,
        3,
        4,
        5
    ],
    "UnlockedLevelsCount": 16,
    "IfFreeBuffsGiven": true,
    "IfFreeCoinsGiven": true,
    "IfGuidePassed": true,
    "IfAdsRemoved": true,
    "LastElapsedTimerTime": 4.968590259552002
}